yoco_python/__init__.py
yoco_python/client.py
yoco_python-0.1.3.dist-info/LICENSE
yoco_python-0.1.3.dist-info/METADATA
yoco_python-0.1.3.dist-info/WHEEL
yoco_python-0.1.3.dist-info/top_level.txt
yoco_python-0.1.3.dist-info/RECORD
