Metadata-Version: 2.1
Name: yoco-python
Version: 0.1.3
Summary: Python SDK for Yoco API
Home-page: https://github.com/QuintenWiggill/yoco-python
Author: Quinten Wiggill
Author-email: qwiggill@gmail.com
License: MIT
Classifier: Intended Audience :: Developers
Classifier: License :: OSI Approved :: MIT License
Classifier: Programming Language :: Python
Classifier: Programming Language :: Python :: 3
Classifier: Programming Language :: Python :: 3.6
Classifier: Programming Language :: Python :: 3.7
Classifier: Programming Language :: Python :: 3.8
Classifier: Programming Language :: Python :: 3.9
Classifier: Operating System :: OS Independent
License-File: LICENSE
Requires-Dist: requests
